{
  "events": [
    {
      "id": "World_Event",
      "active": true,
      "title": "Boost Event",
      "flavor": "Free Boost to Everyone",
      "description": "All Qi gains are doubled for all.",
      "endsAt": "2026-05-32T23:59:00Z",
      "effects": {
        "qiMult": 2
      }
    },
    {
      "id": "freem",
      "active": false,
      "title": "Testing shi",
      "flavor": "Orange",
      "description": "All cultivators receive 10 free Breakthrough attempts, guaranteed to succeed with no Qi cost.",
      "endsAt": "2026-05-31T23:59:00Z",
      "effects": {
        "freeBreakthroughs": 10
      }
    }
  ]
}
