{
  "events": [
    {
      "id": "free",
      "active": false,
      "title": "Weird Shi",
      "flavor": "Too lazy so yeah I'm giving shi",
      "description": "All Qi gains are doubled for all.",
      "endsAt": "2026-05-31T23:59:00Z",
      "effects": {
        "qiMult": 2.0
      }
    },
    {
      "id": "freem",
      "active": true,
      "title": "Testing shi",
      "flavor": "Orange",
      "description": "All cultivators receive 10 free Breakthrough attempts, guaranteed to succeed with no Qi cost.",
      "endsAt": "2026-05-31T23:59:00Z",
      "effects": {
        "freeBreakthroughs": 10
      }
    }
  ]
}
