{
  "name": "Aljifath",
  "accountId": "tD6Y59wIq41L",
  "realmIndex": 29,
  "stage": 4,
  "score": 2940,
  "age": 397.3391077777328,
  "isImmortal": true,
  "difficulty": "normal",
  "updatedAt": 1779703789398,
  "gold": {
    "mantissa": 2.3081203267308004,
    "exponent": 51
  },
  "jade": {
    "mantissa": 2.1030582921521286,
    "exponent": 11
  },
  "qiStones": {
    "mantissa": 8.175829884342653,
    "exponent": 24
  },
  "qi": {
    "mantissa": 1.3281984398481563,
    "exponent": 42
  }
}