{
  "name": "Aljifath",
  "accountId": "tD6Y59wIq41L",
  "realmIndex": 59,
  "stage": 12,
  "score": 6020,
  "age": 482.90833111115444,
  "isImmortal": true,
  "difficulty": "normal",
  "updatedAt": 1779784685298,
  "gold": {
    "mantissa": 5.00349014314275,
    "exponent": 54
  },
  "jade": {
    "mantissa": 4.718011387579581,
    "exponent": 11
  },
  "qiStones": {
    "mantissa": 1.1078904555095053,
    "exponent": 29
  },
  "qi": {
    "mantissa": 2.5188266510355652,
    "exponent": 82
  }
}